{
  "id": "3254037",
  "name": "mi-site",
  "font_family": "iconfont",
  "css_prefix_text": "icon-",
  "description": "",
  "glyphs": [
    {
      "icon_id": "10436",
      "name": "F",
      "font_class": "F",
      "unicode": "e600",
      "unicode_decimal": 58880
    },
    {
      "icon_id": "253561",
      "name": "手机充值_填充",
      "font_class": "shoujichongzhitianchong",
      "unicode": "e6c5",
      "unicode_decimal": 59077
    },
    {
      "icon_id": "577341",
      "name": "购物车",
      "font_class": "gouwuche",
      "unicode": "e73d",
      "unicode_decimal": 59197
    },
    {
      "icon_id": "630094",
      "name": "向右箭头",
      "font_class": "xiangyoujiantou",
      "unicode": "e65f",
      "unicode_decimal": 58975
    },
    {
      "icon_id": "5387553",
      "name": "搜索",
      "font_class": "sousuo",
      "unicode": "eafe",
      "unicode_decimal": 60158
    },
    {
      "icon_id": "11239041",
      "name": "企业",
      "font_class": "qiye",
      "unicode": "e646",
      "unicode_decimal": 58950
    },
    {
      "icon_id": "13581223",
      "name": "更换",
      "font_class": "genghuan",
      "unicode": "e609",
      "unicode_decimal": 58889
    },
    {
      "icon_id": "15609496",
      "name": "安全保障服务(范围逻辑)",
      "font_class": "anquanbaozhangfuwufanweiluoji",
      "unicode": "e6a2",
      "unicode_decimal": 59042
    },
    {
      "icon_id": "18169795",
      "name": "SIM卡,手机卡,电话卡",
      "font_class": "sim-full",
      "unicode": "e946",
      "unicode_decimal": 59718
    }
  ]
}
